pymetar.py
pymetar-1.0.data/data/share/doc/pymetar-1.0/COPYING
pymetar-1.0.data/data/share/doc/pymetar-1.0/README.md
pymetar-1.0.data/data/share/doc/pymetar-1.0/THANKS
pymetar-1.0.data/data/share/doc/pymetar-1.0/librarydoc.txt
pymetar-1.0.data/data/share/man/man1/pymetar.1
pymetar-1.0.data/scripts/pymetar
pymetar-1.0.dist-info/METADATA
pymetar-1.0.dist-info/RECORD
pymetar-1.0.dist-info/WHEEL
pymetar-1.0.dist-info/top_level.txt
