Metadata-Version: 2.1
Name: pymetar
Version: 1.0
Summary: 
